CHANGES.txt
CONTRIBUTORS.txt
MANIFEST.in
README.txt
setup.py
fourdigits/__init__.py
fourdigits.recipe.stud.egg-info/PKG-INFO
fourdigits.recipe.stud.egg-info/SOURCES.txt
fourdigits.recipe.stud.egg-info/dependency_links.txt
fourdigits.recipe.stud.egg-info/entry_points.txt
fourdigits.recipe.stud.egg-info/namespace_packages.txt
fourdigits.recipe.stud.egg-info/not-zip-safe
fourdigits.recipe.stud.egg-info/requires.txt
fourdigits.recipe.stud.egg-info/top_level.txt
fourdigits/recipe/__init__.py
fourdigits/recipe/stud/Makefile
fourdigits/recipe/stud/__init__.py
fourdigits/recipe/stud/tests/__init__.py
fourdigits/recipe/stud/tests/test_docs.py