Metadata-Version: 1.0
Name: fourdigits.recipe.stud
Version: 1.0.2
Summary: Buildout recipe to install stud
Home-page: http://pypi.python.org/pypi/fourdigits.recipe.stud
Author: Franklin Kingma
Author-email: franklin@fourdigits.nl
License: GPL
Keywords: buildout stud ssl proxy
Platform: UNKNOWN
Classifier: Framework :: Buildout
Classifier: Intended Audience :: Developers
Classifier: Topic :: Software Development :: Build Tools
